imitune/__init__.py
imitune/__main__.py
imitune/main.py
imitune/management_tree.py
imitune/oma_dm_client.py
imitune/oma_dm_commands.py
imitune/oma_dm_session.py
imitune/omadm_message.py
imitune-0.2.0.dist-info/licenses/LICENSE
imitune-0.2.0.dist-info/METADATA
imitune-0.2.0.dist-info/WHEEL
imitune-0.2.0.dist-info/entry_points.txt
imitune-0.2.0.dist-info/top_level.txt
imitune-0.2.0.dist-info/RECORD
