Metadata-Version: 2.4
Name: imitune
Version: 0.2.0
Summary: An OMA DM client impersonation tool
Author-email: hotnops <hotnops@protonmail.com>
License: GPL3
Requires-Python: >=3.12
License-File: LICENSE
Requires-Dist: asn1crypto==1.5.1
Requires-Dist: certifi==2025.7.14
Requires-Dist: cffi==1.17.1
Requires-Dist: charset-normalizer==3.4.2
Requires-Dist: cryptography==45.0.5
Requires-Dist: idna==3.10
Requires-Dist: lxml==6.0.0
Requires-Dist: pycparser==2.22
Requires-Dist: requests==2.32.4
Requires-Dist: urllib3==2.5.0
Requires-Dist: xmltodict==0.14.2
Dynamic: license-file
